fabric/analytics/version.py
fabric/analytics/environment/__init__.py
fabric/analytics/environment/constant.py
fabric/analytics/environment/context.py
fabric/analytics/environment/context_plugin.py
fabric/analytics/environment/credentials.py
fabric/analytics/environment/log_handlers.py
fabric/analytics/environment/mwc_credential.py
fabric/analytics/environment/plugin_provider.py
fabric/analytics/environment/token_providers.py
fabric/analytics/environment/base/__init__.py
fabric/analytics/environment/base/context.py
fabric/analytics/environment/base/credentials.py
fabric/analytics/environment/base/log_handlers.py
fabric/analytics/environment/base/plugin.py
fabric/analytics/environment/base/policies.py
fabric/analytics/environment/utils/__init__.py
fabric/analytics/environment/utils/docstring.py
fabric/analytics/environment/utils/plugins.py
fabric/analytics/environment/utils/singleton.py
fabric/analytics/rest/__init__.py
fabric/analytics/rest/client_extension.py
fabric/analytics/rest/fabric_client.py
fabric/analytics/rest/policies.py
fabric/analytics/rest/_generated/__init__.py
fabric/analytics/rest/_generated/_client.py
fabric/analytics/rest/_generated/_configuration.py
fabric/analytics/rest/_generated/_patch.py
fabric/analytics/rest/_generated/_vendor.py
fabric/analytics/rest/_generated/_version.py
fabric/analytics/rest/_generated/py.typed
fabric_analytics_sdk-0.0.3.post1.dist-info/licenses/LICENSE.txt
fabric_analytics_sdk-0.0.3.post1.dist-info/METADATA
fabric_analytics_sdk-0.0.3.post1.dist-info/WHEEL
fabric_analytics_sdk-0.0.3.post1.dist-info/entry_points.txt
fabric_analytics_sdk-0.0.3.post1.dist-info/top_level.txt
fabric_analytics_sdk-0.0.3.post1.dist-info/RECORD
