Metadata-Version: 2.4
Name: fabric-analytics-sdk
Version: 0.0.3.post1
Summary: SDK for the Fabric Analytics Client
Author: Microsoft Corporation
License: MICROSOFT SOFTWARE LICENSE TERMS
Classifier: Development Status :: 3 - Alpha
Classifier: Intended Audience :: Developers
Classifier: Intended Audience :: Education
Classifier: Intended Audience :: Science/Research
Classifier: Programming Language :: Python :: 3.10
Classifier: Programming Language :: Python :: 3 :: Only
Requires-Python: <3.15,>=3.10
License-File: LICENSE.txt
Requires-Dist: azure-core
Requires-Dist: azure-identity
Provides-Extra: online-notebook
Requires-Dist: fabric-analytics-notebook-plugin; extra == "online-notebook"
Provides-Extra: vscode
Requires-Dist: fabric-analytics-vscode-plugin; extra == "vscode"
Provides-Extra: data-agent
Requires-Dist: fabric-analytics-data-agent-container-plugin; extra == "data-agent"
Provides-Extra: ado-pipeline
Requires-Dist: fabric-analytics-msft-only-ado-pipeline-plugin; extra == "ado-pipeline"
Dynamic: license-file
